flyteplugins/connectors/__init__.py
flyteplugins/connectors/bigquery/__init__.py
flyteplugins/connectors/bigquery/connector.py
flyteplugins/connectors/bigquery/task.py
flyteplugins/connectors/databricks/__init__.py
flyteplugins/connectors/databricks/connector.py
flyteplugins/connectors/databricks/task.py
flyteplugins/connectors/snowflake/__init__.py
flyteplugins/connectors/snowflake/connector.py
flyteplugins/connectors/snowflake/task.py
flyteplugins_connectors-2.0.0b53.dist-info/METADATA
flyteplugins_connectors-2.0.0b53.dist-info/WHEEL
flyteplugins_connectors-2.0.0b53.dist-info/entry_points.txt
flyteplugins_connectors-2.0.0b53.dist-info/top_level.txt
flyteplugins_connectors-2.0.0b53.dist-info/RECORD
