Metadata-Version: 2.4
Name: flyteplugins-connectors
Version: 2.0.0b53
Summary: Connector plugin for flyte
Author-email: Kevin Su <pingsutw@users.noreply.github.com>
Requires-Python: >=3.10
Requires-Dist: flyte
Requires-Dist: grpcio-health-checking
Requires-Dist: prometheus-client
Provides-Extra: bigquery
Requires-Dist: google-cloud-bigquery; extra == "bigquery"
Requires-Dist: google-cloud-bigquery-storage; extra == "bigquery"
Provides-Extra: databricks
Requires-Dist: aiohttp; extra == "databricks"
Requires-Dist: nest-asyncio; extra == "databricks"
Requires-Dist: flyteplugins-spark; extra == "databricks"
Provides-Extra: snowflake
Requires-Dist: snowflake-connector-python; extra == "snowflake"
Requires-Dist: cryptography; extra == "snowflake"
